pdfdataprocess/__init__.py
pdfdataprocess/cli.py
pdfdataprocess/process.py
pdfdataprocess-0.1.2.dist-info/METADATA
pdfdataprocess-0.1.2.dist-info/WHEEL
pdfdataprocess-0.1.2.dist-info/entry_points.txt
pdfdataprocess-0.1.2.dist-info/RECORD
