Metadata-Version: 2.1
Name: pdfdataprocess
Version: 0.1.2
Summary: 
Home-page: https://github.com/arnos-stuff/pdf-data-process.git
Author: arnos-stuff
Author-email: bcda0276@gmail.com
Requires-Python: >=3.11,<4.0
Classifier: Programming Language :: Python :: 3
Classifier: Programming Language :: Python :: 3.11
Requires-Dist: nodejs-bin (>=18.4.0a4,<19.0.0)
Requires-Dist: numpy (>=1.24.3,<2.0.0)
Requires-Dist: pandas (>=2.0.1,<3.0.0)
Requires-Dist: tqdm (>=4.65.0,<5.0.0)
Requires-Dist: typer (>=0.9.0,<0.10.0)
